geo/__init__.py
geo/alt.py
geo/geodata.py
geo_nuuuwan-1.0.5.dist-info/LICENSE
geo_nuuuwan-1.0.5.dist-info/METADATA
geo_nuuuwan-1.0.5.dist-info/WHEEL
geo_nuuuwan-1.0.5.dist-info/top_level.txt
geo_nuuuwan-1.0.5.dist-info/RECORD
