Metadata-Version: 2.1
Name: geo-nuuuwan
Version: 1.0.5
Summary: Python library for drawing maps of Sri Lanka.
Home-page: https://github.com/nuuuwan/geo
Author: Nuwan I. Senaratna
Author-email: nuuuwan@gmail.com
Project-URL: Bug Tracker, https://github.com/nuuuwan/geo/issues
Classifier: Programming Language :: Python :: 3
Classifier: License :: OSI Approved :: MIT License
Classifier: Operating System :: OS Independent
Requires-Python: >=3.6
License-File: LICENSE
Requires-Dist: geopandas
Requires-Dist: shapely
Requires-Dist: utils-nuuuwan
Requires-Dist: gig-nuuuwan
